cast_control/__init__.py
cast_control/__main__.py
cast_control/adapter.py
cast_control/base.py
cast_control/protocols.py
cast_control/py.typed
cast_control/app/__init__.py
cast_control/app/cli.py
cast_control/app/daemon.py
cast_control/app/run.py
cast_control/app/state.py
cast_control/assets/mpris_plasma.png
cast_control/assets/mpris_widget.png
cast_control/assets/template.desktop
cast_control/assets/icon/authors.yml
cast_control/assets/icon/cc-black.svg
cast_control/assets/icon/cc-template.svg
cast_control/assets/icon/cc-white.svg
cast_control/assets/icon/licenses.yml
cast_control/device/__init__.py
cast_control/device/base.py
cast_control/device/device.py
cast_control/device/listeners.py
cast_control/device/wrapper.py
cast_control-0.16.0.dist-info/METADATA
cast_control-0.16.0.dist-info/WHEEL
cast_control-0.16.0.dist-info/entry_points.txt
cast_control-0.16.0.dist-info/licenses/LICENSE
cast_control-0.16.0.dist-info/RECORD
