Metadata-Version: 2.3
Name: cast_control
Version: 0.16.0
Summary: 📺 Control Chromecasts from the Linux desktop and console
Project-URL: Homepage, https://cast.firstbyte.dev
Project-URL: Source, https://github.com/alexdelorenzo/cast_control
Author-email: Alex DeLorenzo <projects@alexdelorenzo.dev>
License: AGPL-3.0
License-File: LICENSE
Requires-Python: >=3.12
Requires-Dist: aiopath>=0.7.6; python_version >= '3.12'
Requires-Dist: app-paths<0.1.0,>=0.0.8
Requires-Dist: appdirs<1.5.0,>=1.4.4
Requires-Dist: click<9.0.0,>=8.1.7
Requires-Dist: daemons<1.4.0,>=1.3.2
Requires-Dist: iteration-utilities<0.13.0,>=0.12.0
Requires-Dist: mpris-server<=0.10.0,>=0.9.0
Requires-Dist: pychromecast<15.0.0,>=14.0.2
Requires-Dist: pydbus<0.7.0,>=0.6.0
Requires-Dist: pygobject>=3.34.0
Requires-Dist: rich<14.0.0,>=13.6.0
Requires-Dist: validators<0.23.0,>=0.22.0
